censusprotocollib-1.0.0.data/data/my_data/data_file
cplib/__init__.py
cplib/census.py
cplib/crypto.py
censusprotocollib-1.0.0.dist-info/WHEEL
censusprotocollib-1.0.0.dist-info/metadata.json
censusprotocollib-1.0.0.dist-info/entry_points.txt
censusprotocollib-1.0.0.dist-info/top_level.txt
censusprotocollib-1.0.0.dist-info/DESCRIPTION.rst
censusprotocollib-1.0.0.dist-info/METADATA
censusprotocollib-1.0.0.dist-info/RECORD
sample/version_test.py
sample/__init__.py
sample/buy_test.py
sample/package_data.dat
sample/vend_test.py
