Metadata-Version: 2.0
Name: censusprotocollib
Version: 1.0.0
Summary: Simple interface for using the Census Protocol
Home-page: https://github.com/censusprotocol/cplibrary
Author: The Census Protocol FoundTION
Author-email: cp-announce@googlegroups.com
License: MIT
Keywords: crypto development
Platform: UNKNOWN
Classifier: Development Status :: 3 - Alpha
Classifier: Intended Audience :: Developers
Classifier: Topic :: Software Development :: Build Tools
Classifier: License :: OSI Approved :: MIT License
Classifier: Programming Language :: Python :: 2
Classifier: Programming Language :: Python :: 2.6
Classifier: Programming Language :: Python :: 2.7
Classifier: Programming Language :: Python :: 3
Classifier: Programming Language :: Python :: 3.2
Classifier: Programming Language :: Python :: 3.3
Classifier: Programming Language :: Python :: 3.4
Requires-Dist: pybitcointools
Requires-Dist: requests
Requires-Dist: uuid
Requires-Dist: ecdsa
Provides-Extra: test
Requires-Dist: coverage; extra == 'test'
Provides-Extra: dev
Requires-Dist: check-manifest; extra == 'dev'
